more.basicauth-0.5-py3.7-nspkg.pth
more/basicauth/__init__.py
more/basicauth/main.py
more/basicauth/tests/test_basicauth.py
more.basicauth-0.5.dist-info/LICENSE.txt
more.basicauth-0.5.dist-info/METADATA
more.basicauth-0.5.dist-info/WHEEL
more.basicauth-0.5.dist-info/namespace_packages.txt
more.basicauth-0.5.dist-info/top_level.txt
more.basicauth-0.5.dist-info/RECORD
