Metadata-Version: 2.1
Name: more.basicauth
Version: 0.5
Summary: Basic Auth Identity Policy for Morepath
Home-page: https://github.com/morepath/more.basicauth
Author: Morepath developers
Author-email: morepath@googlegroups.com
License: BSD
Keywords: morepath basicauth identity authentication
Platform: UNKNOWN
Classifier: Intended Audience :: Developers
Classifier: License :: OSI Approved :: BSD License
Classifier: Environment :: Web Environment
Classifier: Topic :: Software Development :: Libraries :: Application Frameworks
Classifier: Topic :: Internet :: WWW/HTTP :: WSGI
Classifier: Programming Language :: Python :: 3.4
Classifier: Programming Language :: Python :: 3.5
Classifier: Programming Language :: Python :: 3.6
Classifier: Programming Language :: Python :: 3.7
Classifier: Programming Language :: Python :: 3.8
Classifier: Programming Language :: Python :: Implementation :: PyPy
Classifier: Development Status :: 5 - Production/Stable
Requires-Dist: morepath (>=0.19)
Provides-Extra: coverage
Requires-Dist: pytest-cov ; extra == 'coverage'
Provides-Extra: pep8
Requires-Dist: flake8 ; extra == 'pep8'
Requires-Dist: black ; extra == 'pep8'
Provides-Extra: test
Requires-Dist: pytest (>=2.9.1) ; extra == 'test'
Requires-Dist: pytest-remove-stale-bytecode ; extra == 'test'
Requires-Dist: WebTest (>=2.0.14) ; extra == 'test'
